pretty_repr/__init__.py
pretty_repr/main.py
pretty_repr/test_main.py
pretty_repr-1.0.6.dist-info/LICENSE
pretty_repr-1.0.6.dist-info/METADATA
pretty_repr-1.0.6.dist-info/WHEEL
pretty_repr-1.0.6.dist-info/top_level.txt
pretty_repr-1.0.6.dist-info/RECORD
