Metadata-Version: 2.1
Name: pretty_repr
Version: 1.0.6
Summary: The package that allows you to create clear and informative methods for your own classes in Python.
Home-page: https://github.com/AlbertFarkhutdinov/pretty_repr
Author: Albert Farkhutdinov
Author-email: albertfarhutdinov@gmail.com
Classifier: Development Status :: 5 - Production/Stable
Classifier: Programming Language :: Python :: 3.9
Classifier: License :: OSI Approved :: MIT License
Classifier: Operating System :: OS Independent
Requires-Python: >=3.6
License-File: LICENSE
Requires-Dist: pytest<8,>6
